{
  "fetchedAt": "2026-03-24T23:13:00.130Z",
  "_meta": {
    "sources_scanned": 2,
    "source_list": [
      "amplitude",
      "linear"
    ],
    "signal_count": 30
  },
  "signals": [
    {
      "source": "linear",
      "title": "ENG-9297: Move runbooks to markdown in internal-docs",
      "priority": "URGENT",
      "state": "Ready for Work",
      "assignee": "Wei Lu",
      "team": "Engineering",
      "timestamp": "2026-03-24T23:05:34.002Z",
      "evidence": [
        {
          "label": "ENG-9297",
          "url": "https://linear.app/siftstack/issue/ENG-9297/move-runbooks-to-markdown-in-internal-docs",
          "source": "linear"
        }
      ]
    },
    {
      "source": "linear",
      "title": "DES-152: [UX] Multi-Run Calculated Channels",
      "priority": "HIGH",
      "state": "In Progress",
      "assignee": "Clinton Naugle",
      "team": "Design",
      "timestamp": "2026-03-24T23:03:40.922Z",
      "evidence": [
        {
          "label": "DES-152",
          "url": "https://linear.app/siftstack/issue/DES-152/ux-multi-run-calculated-channels",
          "source": "linear"
        }
      ]
    },
    {
      "source": "linear",
      "title": "DES-149: [UX] Run to Run Rules",
      "priority": "HIGH",
      "state": "In Progress",
      "assignee": "Clinton Naugle",
      "team": "Design",
      "timestamp": "2026-03-24T23:03:37.905Z",
      "evidence": [
        {
          "label": "DES-149",
          "url": "https://linear.app/siftstack/issue/DES-149/ux-run-to-run-rules",
          "source": "linear"
        }
      ]
    },
    {
      "source": "linear",
      "title": "DES-113: ULA customer feedback on Family Visualization",
      "priority": "HIGH",
      "state": "Ready for Work",
      "assignee": "Clinton Naugle",
      "team": "Design",
      "timestamp": "2026-03-24T23:01:47.783Z",
      "evidence": [
        {
          "label": "DES-113",
          "url": "https://linear.app/siftstack/issue/DES-113/ula-customer-feedback-on-family-visualization",
          "source": "linear"
        }
      ]
    },
    {
      "source": "linear",
      "title": "ENG-9420: Improve \"Apply Default to All\" Experience",
      "priority": "HIGH",
      "state": "In Verification",
      "assignee": "Clinton Naugle",
      "team": "Engineering",
      "timestamp": "2026-03-24T23:00:20.490Z",
      "evidence": [
        {
          "label": "ENG-9420",
          "url": "https://linear.app/siftstack/issue/ENG-9420/improve-apply-default-to-all-experience",
          "source": "linear"
        }
      ]
    },
    {
      "source": "linear",
      "title": "ENG-9556: [FE] Inform users that Family Data is in Beta",
      "priority": "URGENT",
      "state": "In Verification",
      "assignee": "Clinton Naugle",
      "team": "Engineering",
      "timestamp": "2026-03-24T22:59:48.118Z",
      "evidence": [
        {
          "label": "ENG-9556",
          "url": "https://linear.app/siftstack/issue/ENG-9556/fe-inform-users-that-family-data-is-in-beta",
          "source": "linear"
        }
      ]
    },
    {
      "source": "linear",
      "title": "ENG-9603: Sift Edge GHA Workflows + Branch protections + commit hooks",
      "priority": "URGENT",
      "state": "In Review",
      "assignee": "benjamin@siftstack.com",
      "team": "Engineering",
      "timestamp": "2026-03-24T22:55:47.143Z",
      "evidence": [
        {
          "label": "ENG-9603",
          "url": "https://linear.app/siftstack/issue/ENG-9603/sift-edge-gha-workflows-branch-protections-commit-hooks",
          "source": "linear"
        }
      ]
    },
    {
      "source": "linear",
      "title": "ENG-9569: v0.1.0 release for Sift CLI",
      "priority": "URGENT",
      "state": "In Review",
      "assignee": "benjamin@siftstack.com",
      "team": "Engineering",
      "timestamp": "2026-03-24T22:50:25.848Z",
      "evidence": [
        {
          "label": "ENG-9569",
          "url": "https://linear.app/siftstack/issue/ENG-9569/v010-release-for-sift-cli",
          "source": "linear"
        }
      ]
    },
    {
      "source": "linear",
      "title": "ENG-9604: Automate creation of organization user as part of GKE deployment",
      "priority": "URGENT",
      "state": "In Progress",
      "assignee": "sfu@lardoandassociates.com",
      "team": "Engineering",
      "timestamp": "2026-03-24T22:43:08.197Z",
      "evidence": [
        {
          "label": "ENG-9604",
          "url": "https://linear.app/siftstack/issue/ENG-9604/automate-creation-of-organization-user-as-part-of-gke-deployment",
          "source": "linear"
        }
      ]
    },
    {
      "source": "linear",
      "title": "ENG-9546: Ephemeral disable certs for keycloak, frontend, and backend",
      "priority": "URGENT",
      "state": "In Verification",
      "assignee": "sfu@lardoandassociates.com",
      "team": "Engineering",
      "timestamp": "2026-03-24T22:43:05.006Z",
      "evidence": [
        {
          "label": "ENG-9546",
          "url": "https://linear.app/siftstack/issue/ENG-9546/ephemeral-disable-certs-for-keycloak-frontend-and-backend",
          "source": "linear"
        }
      ]
    },
    {
      "source": "linear",
      "title": "DOC-16: Families documentation",
      "priority": "URGENT",
      "state": "In Progress",
      "assignee": "Michael Cretzman",
      "team": "Documentation",
      "timestamp": "2026-03-24T22:27:48.377Z",
      "evidence": [
        {
          "label": "DOC-16",
          "url": "https://linear.app/siftstack/issue/DOC-16/families-documentation",
          "source": "linear"
        }
      ]
    },
    {
      "source": "linear",
      "title": "ENG-9499: Link to sift docs on families from family page",
      "priority": "URGENT",
      "state": "Ready for Work",
      "assignee": "Bill Raj-Derouin",
      "team": "Engineering",
      "timestamp": "2026-03-24T22:27:17.874Z",
      "evidence": [
        {
          "label": "ENG-9499",
          "url": "https://linear.app/siftstack/issue/ENG-9499/link-to-sift-docs-on-families-from-family-page",
          "source": "linear"
        }
      ]
    },
    {
      "source": "linear",
      "title": "ENG-9600: Allow arbitrary file types for file attachment uploads",
      "priority": "URGENT",
      "state": "In Review",
      "assignee": "Wei Lu",
      "team": "Engineering",
      "timestamp": "2026-03-24T22:16:37.809Z",
      "evidence": [
        {
          "label": "ENG-9600",
          "url": "https://linear.app/siftstack/issue/ENG-9600/allow-arbitrary-file-types-for-file-attachment-uploads",
          "source": "linear"
        }
      ]
    },
    {
      "source": "linear",
      "title": "ENG-9530: [FE] Candidate run members page",
      "priority": "HIGH",
      "state": "In Progress",
      "assignee": "Alexa Agnew",
      "team": "Engineering",
      "timestamp": "2026-03-24T22:14:09.015Z",
      "evidence": [
        {
          "label": "ENG-9530",
          "url": "https://linear.app/siftstack/issue/ENG-9530/fe-candidate-run-members-page",
          "source": "linear"
        }
      ]
    },
    {
      "source": "linear",
      "title": "ENG-9608: E2 Annotations: Redo annotations caching strategy",
      "priority": "HIGH",
      "state": "In Verification",
      "assignee": "broch@siftstack.com",
      "team": "Engineering",
      "timestamp": "2026-03-24T21:49:52.403Z",
      "evidence": [
        {
          "label": "ENG-9608",
          "url": "https://linear.app/siftstack/issue/ENG-9608/e2-annotations-redo-annotations-caching-strategy",
          "source": "linear"
        }
      ]
    },
    {
      "source": "linear",
      "title": "ENG-9585: evaluate checkly as e2e external integration testing",
      "priority": "URGENT",
      "state": "Ready for Work",
      "assignee": "Felix Wong",
      "team": "Engineering",
      "timestamp": "2026-03-24T21:45:18.819Z",
      "evidence": [
        {
          "label": "ENG-9585",
          "url": "https://linear.app/siftstack/issue/ENG-9585/evaluate-checkly-as-e2e-external-integration-testing",
          "source": "linear"
        }
      ]
    },
    {
      "source": "linear",
      "title": "ENG-9618: Fix Calculated Channels created without panel",
      "priority": "URGENT",
      "state": "In Progress",
      "assignee": "leo@siftstack.com",
      "team": "Engineering",
      "timestamp": "2026-03-24T21:39:01.476Z",
      "evidence": [
        {
          "label": "ENG-9618",
          "url": "https://linear.app/siftstack/issue/ENG-9618/fix-calculated-channels-created-without-panel",
          "source": "linear"
        }
      ]
    },
    {
      "source": "linear",
      "title": "ENG-9607: Remove TrackDataIngestion call",
      "priority": "HIGH",
      "state": "In Verification",
      "assignee": "Jonathan Deng",
      "team": "Engineering",
      "timestamp": "2026-03-24T21:22:31.973Z",
      "evidence": [
        {
          "label": "ENG-9607",
          "url": "https://linear.app/siftstack/issue/ENG-9607/remove-trackdataingestion-call",
          "source": "linear"
        }
      ]
    },
    {
      "source": "linear",
      "title": "ENG-9616: Remove ArbPB use of \"ingest_config_flows\" table",
      "priority": "URGENT",
      "state": "In Progress",
      "assignee": "Bryce Turley",
      "team": "Engineering",
      "timestamp": "2026-03-24T20:56:29.200Z",
      "evidence": [
        {
          "label": "ENG-9616",
          "url": "https://linear.app/siftstack/issue/ENG-9616/remove-arbpb-use-of-ingest-config-flows-table",
          "source": "linear"
        }
      ]
    },
    {
      "source": "linear",
      "title": "ENG-9125: Event Feature Flagged Experiences",
      "priority": "HIGH",
      "state": "Ready for Work",
      "assignee": "jon@siftstack.com",
      "team": "Engineering",
      "timestamp": "2026-03-24T20:49:07.561Z",
      "evidence": [
        {
          "label": "ENG-9125",
          "url": "https://linear.app/siftstack/issue/ENG-9125/event-feature-flagged-experiences",
          "source": "linear"
        }
      ]
    },
    {
      "source": "linear",
      "title": "ENG-9124: Implement Session Replay for Feature Flagged Experiences;",
      "priority": "HIGH",
      "state": "Ready for Work",
      "assignee": "Kenn Zamora",
      "team": "Engineering",
      "timestamp": "2026-03-24T20:49:05.364Z",
      "evidence": [
        {
          "label": "ENG-9124",
          "url": "https://linear.app/siftstack/issue/ENG-9124/implement-session-replay-for-feature-flagged-experiences",
          "source": "linear"
        }
      ]
    },
    {
      "source": "linear",
      "title": "ENG-9122: [Discovery] Feature Flag Front-End Prototypes",
      "priority": "HIGH",
      "state": "Ready for Work",
      "assignee": "jon@siftstack.com",
      "team": "Engineering",
      "timestamp": "2026-03-24T20:49:02.895Z",
      "evidence": [
        {
          "label": "ENG-9122",
          "url": "https://linear.app/siftstack/issue/ENG-9122/discovery-feature-flag-front-end-prototypes",
          "source": "linear"
        }
      ]
    },
    {
      "source": "linear",
      "title": "ENG-9550: Explore pathname and link migration",
      "priority": "URGENT",
      "state": "In Progress",
      "assignee": "evan@siftstack.com",
      "team": "Engineering",
      "timestamp": "2026-03-24T20:41:12.991Z",
      "evidence": [
        {
          "label": "ENG-9550",
          "url": "https://linear.app/siftstack/issue/ENG-9550/explore-pathname-and-link-migration",
          "source": "linear"
        }
      ]
    },
    {
      "source": "linear",
      "title": "ENG-9613: Build internal tool for onboarding new customers to IdP",
      "priority": "URGENT",
      "state": "Ready for Work",
      "team": "Engineering",
      "timestamp": "2026-03-24T20:31:07.732Z",
      "evidence": [
        {
          "label": "ENG-9613",
          "url": "https://linear.app/siftstack/issue/ENG-9613/build-internal-tool-for-onboarding-new-customers-to-idp",
          "source": "linear"
        }
      ]
    },
    {
      "source": "linear",
      "title": "ENG-9614: Create internal metrics/alerts for Idp Is succeeding/failing",
      "priority": "URGENT",
      "state": "Ready for Work",
      "team": "Engineering",
      "timestamp": "2026-03-24T20:31:07.716Z",
      "evidence": [
        {
          "label": "ENG-9614",
          "url": "https://linear.app/siftstack/issue/ENG-9614/create-internal-metricsalerts-for-idp-is-succeedingfailing",
          "source": "linear"
        }
      ]
    },
    {
      "source": "linear",
      "title": "ENG-8081: IdP integration for TEC",
      "priority": "HIGH",
      "state": "Ready for Work",
      "assignee": "Jonathan Deng",
      "team": "Engineering",
      "timestamp": "2026-03-24T20:31:07.690Z",
      "evidence": [
        {
          "label": "ENG-8081",
          "url": "https://linear.app/siftstack/issue/ENG-8081/idp-integration-for-tec",
          "source": "linear"
        }
      ]
    },
    {
      "source": "linear",
      "title": "ENG-8157: Support IdP for Astrolab SSO",
      "priority": "HIGH",
      "state": "Ready for Work",
      "assignee": "Alex Khan",
      "team": "Engineering",
      "timestamp": "2026-03-24T20:31:07.659Z",
      "evidence": [
        {
          "label": "ENG-8157",
          "url": "https://linear.app/siftstack/issue/ENG-8157/support-idp-for-astrolab-sso",
          "source": "linear"
        }
      ]
    },
    {
      "source": "linear",
      "title": "ENG-9296: Internal MCP server MVP",
      "priority": "URGENT",
      "state": "In Progress",
      "assignee": "adam@siftstack.com",
      "team": "Engineering",
      "timestamp": "2026-03-24T20:29:09.736Z",
      "evidence": [
        {
          "label": "ENG-9296",
          "url": "https://linear.app/siftstack/issue/ENG-9296/internal-mcp-server-mvp",
          "source": "linear"
        }
      ]
    },
    {
      "source": "linear",
      "title": "ENG-9292: Agent-assisted incident response proof of concept",
      "priority": "URGENT",
      "state": "Ready for Work",
      "team": "Engineering",
      "timestamp": "2026-03-24T20:29:09.736Z",
      "evidence": [
        {
          "label": "ENG-9292",
          "url": "https://linear.app/siftstack/issue/ENG-9292/agent-assisted-incident-response-proof-of-concept",
          "source": "linear"
        }
      ]
    },
    {
      "source": "linear",
      "title": "ENG-9543: Document AWS credentials break-glass",
      "priority": "URGENT",
      "state": "Ready for Work",
      "assignee": "Bill Raj-Derouin",
      "team": "Engineering",
      "timestamp": "2026-03-24T19:58:15.531Z",
      "evidence": [
        {
          "label": "ENG-9543",
          "url": "https://linear.app/siftstack/issue/ENG-9543/document-aws-credentials-break-glass",
          "source": "linear"
        }
      ]
    }
  ],
  "amplitude": {
    "dau": {
      "chart": "a08uik9s",
      "data": {
        "series": [
          [
            {
              "setId": "",
              "value": 287
            },
            {
              "setId": "",
              "value": 599
            },
            {
              "setId": "",
              "value": 549
            },
            {
              "setId": "",
              "value": 529
            },
            {
              "setId": "",
              "value": 573
            },
            {
              "setId": "",
              "value": 607
            },
            {
              "setId": "",
              "value": 601
            },
            {
              "setId": "",
              "value": 579
            },
            {
              "setId": "",
              "value": 614
            },
            {
              "setId": "",
              "value": 705
            },
            {
              "setId": "",
              "value": 649
            },
            {
              "setId": "",
              "value": 762
            },
            {
              "setId": "",
              "value": 439
            }
          ]
        ],
        "seriesCollapsed": [
          [
            {
              "setId": "",
              "value": 2063
            }
          ]
        ],
        "seriesLabels": [
          0
        ],
        "seriesMeta": [
          {
            "segmentIndex": 0,
            "eventIndex": 0
          }
        ],
        "xValues": [
          "2025-12-29",
          "2026-01-05",
          "2026-01-12",
          "2026-01-19",
          "2026-01-26",
          "2026-02-02",
          "2026-02-09",
          "2026-02-16",
          "2026-02-23",
          "2026-03-02",
          "2026-03-09",
          "2026-03-16",
          "2026-03-23"
        ]
      }
    },
    "newUsers": {
      "chart": "u5ctmoro",
      "data": {
        "series": [
          [
            {
              "setId": "",
              "value": 108
            },
            {
              "setId": "",
              "value": 323
            },
            {
              "setId": "",
              "value": 353
            },
            {
              "setId": "",
              "value": 323
            },
            {
              "setId": "",
              "value": 314
            },
            {
              "setId": "",
              "value": 294
            },
            {
              "setId": "",
              "value": 122
            },
            {
              "setId": "",
              "value": 145
            },
            {
              "setId": "",
              "value": 382
            },
            {
              "setId": "",
              "value": 383
            },
            {
              "setId": "",
              "value": 357
            },
            {
              "setId": "",
              "value": 353
            },
            {
              "setId": "",
              "value": 315
            },
            {
              "setId": "",
              "value": 125
            },
            {
              "setId": "",
              "value": 137
            },
            {
              "setId": "",
              "value": 342
            },
            {
              "setId": "",
              "value": 343
            },
            {
              "setId": "",
              "value": 365
            },
            {
              "setId": "",
              "value": 352
            },
            {
              "setId": "",
              "value": 323
            },
            {
              "setId": "",
              "value": 113
            },
            {
              "setId": "",
              "value": 108
            },
            {
              "setId": "",
              "value": 364
            },
            {
              "setId": "",
              "value": 379
            },
            {
              "setId": "",
              "value": 386
            },
            {
              "setId": "",
              "value": 411
            },
            {
              "setId": "",
              "value": 365
            },
            {
              "setId": "",
              "value": 132
            },
            {
              "setId": "",
              "value": 132
            },
            {
              "setId": "",
              "value": 374
            },
            {
              "setId": "",
              "value": 322
            }
          ]
        ],
        "seriesCollapsed": [
          [
            {
              "setId": "",
              "value": 1330
            }
          ]
        ],
        "seriesLabels": [
          0
        ],
        "seriesMeta": [
          {
            "segmentIndex": 0,
            "eventIndex": 0
          }
        ],
        "xValues": [
          "2026-02-22",
          "2026-02-23",
          "2026-02-24",
          "2026-02-25",
          "2026-02-26",
          "2026-02-27",
          "2026-02-28",
          "2026-03-01",
          "2026-03-02",
          "2026-03-03",
          "2026-03-04",
          "2026-03-05",
          "2026-03-06",
          "2026-03-07",
          "2026-03-08",
          "2026-03-09",
          "2026-03-10",
          "2026-03-11",
          "2026-03-12",
          "2026-03-13",
          "2026-03-14",
          "2026-03-15",
          "2026-03-16",
          "2026-03-17",
          "2026-03-18",
          "2026-03-19",
          "2026-03-20",
          "2026-03-21",
          "2026-03-22",
          "2026-03-23",
          "2026-03-24"
        ]
      }
    },
    "featureAdoption": {
      "chart": "5ab27lld",
      "data": {
        "series": [
          [
            {
              "setId": "",
              "value": 30
            },
            {
              "setId": "",
              "value": 128
            },
            {
              "setId": "",
              "value": 57
            },
            {
              "setId": "",
              "value": 67
            },
            {
              "setId": "",
              "value": 93
            },
            {
              "setId": "",
              "value": 136
            },
            {
              "setId": "",
              "value": 94
            },
            {
              "setId": "",
              "value": 87
            },
            {
              "setId": "",
              "value": 94
            },
            {
              "setId": "",
              "value": 118
            },
            {
              "setId": "",
              "value": 101
            },
            {
              "setId": "",
              "value": 166
            },
            {
              "setId": "",
              "value": 40
            }
          ]
        ],
        "seriesCollapsed": [
          [
            {
              "setId": "",
              "value": 1211
            }
          ]
        ],
        "seriesLabels": [
          0
        ],
        "seriesMeta": [
          {
            "segmentIndex": 0,
            "eventIndex": 0
          }
        ],
        "xValues": [
          "2025-12-29",
          "2026-01-05",
          "2026-01-12",
          "2026-01-19",
          "2026-01-26",
          "2026-02-02",
          "2026-02-09",
          "2026-02-16",
          "2026-02-23",
          "2026-03-02",
          "2026-03-09",
          "2026-03-16",
          "2026-03-23"
        ]
      }
    },
    "retention": {
      "chart": "dogczzd8",
      "data": {
        "series": [
          [
            4474.877482269503,
            4683.577634868421,
            5511.864267062314,
            5738.833516666667,
            5738.7081,
            5361.95617571885,
            5453.182705014749,
            6097.445726708074,
            6475.56686039886,
            6928.739205263158,
            6264.648006116208,
            5513.1750660377365,
            2582.191648648649
          ]
        ],
        "seriesCollapsed": [
          [
            {
              "setId": "",
              "value": 23812.459799136068
            }
          ]
        ],
        "seriesMeta": [
          {
            "segmentIndex": 0,
            "sessionIndex": 0
          }
        ],
        "xValues": [
          "2025-12-29T00:00:00",
          "2026-01-05T00:00:00",
          "2026-01-12T00:00:00",
          "2026-01-19T00:00:00",
          "2026-01-26T00:00:00",
          "2026-02-02T00:00:00",
          "2026-02-09T00:00:00",
          "2026-02-16T00:00:00",
          "2026-02-23T00:00:00",
          "2026-03-02T00:00:00",
          "2026-03-09T00:00:00",
          "2026-03-16T00:00:00",
          "2026-03-23T00:00:00"
        ]
      }
    },
    "collaboration": {
      "chart": "e74ntz32",
      "data": {
        "series": [
          [
            {
              "setId": "",
              "value": 157
            },
            {
              "setId": "",
              "value": 321
            },
            {
              "setId": "",
              "value": 369
            },
            {
              "setId": "",
              "value": 340
            },
            {
              "setId": "",
              "value": 355
            },
            {
              "setId": "",
              "value": 361
            },
            {
              "setId": "",
              "value": 379
            },
            {
              "setId": "",
              "value": 333
            },
            {
              "setId": "",
              "value": 388
            },
            {
              "setId": "",
              "value": 431
            },
            {
              "setId": "",
              "value": 433
            },
            {
              "setId": "",
              "value": 460
            },
            {
              "setId": "",
              "value": 262
            }
          ],
          [
            {
              "setId": "",
              "value": 24
            },
            {
              "setId": "",
              "value": 46
            },
            {
              "setId": "",
              "value": 45
            },
            {
              "setId": "",
              "value": 39
            },
            {
              "setId": "",
              "value": 48
            },
            {
              "setId": "",
              "value": 43
            },
            {
              "setId": "",
              "value": 63
            },
            {
              "setId": "",
              "value": 48
            },
            {
              "setId": "",
              "value": 70
            },
            {
              "setId": "",
              "value": 61
            },
            {
              "setId": "",
              "value": 48
            },
            {
              "setId": "",
              "value": 71
            },
            {
              "setId": "",
              "value": 27
            }
          ],
          [
            {
              "setId": "",
              "value": 9
            },
            {
              "setId": "",
              "value": 28
            },
            {
              "setId": "",
              "value": 28
            },
            {
              "setId": "",
              "value": 39
            },
            {
              "setId": "",
              "value": 29
            },
            {
              "setId": "",
              "value": 54
            },
            {
              "setId": "",
              "value": 39
            },
            {
              "setId": "",
              "value": 45
            },
            {
              "setId": "",
              "value": 56
            },
            {
              "setId": "",
              "value": 48
            },
            {
              "setId": "",
              "value": 54
            },
            {
              "setId": "",
              "value": 53
            },
            {
              "setId": "",
              "value": 16
            }
          ],
          [
            {
              "setId": "",
              "value": 0
            },
            {
              "setId": "",
              "value": 0
            },
            {
              "setId": "",
              "value": 0
            },
            {
              "setId": "",
              "value": 0
            },
            {
              "setId": "",
              "value": 1
            },
            {
              "setId": "",
              "value": 0
            },
            {
              "setId": "",
              "value": 0
            },
            {
              "setId": "",
              "value": 4
            },
            {
              "setId": "",
              "value": 0
            },
            {
              "setId": "",
              "value": 1
            },
            {
              "setId": "",
              "value": 0
            },
            {
              "setId": "",
              "value": 0
            },
            {
              "setId": "",
              "value": 0
            }
          ]
        ],
        "seriesCollapsed": [
          [
            {
              "setId": "",
              "value": 1016
            }
          ],
          [
            {
              "setId": "",
              "value": 252
            }
          ],
          [
            {
              "setId": "",
              "value": 228
            }
          ],
          [
            {
              "setId": "",
              "value": 6
            }
          ]
        ],
        "seriesLabels": [
          0,
          0,
          0,
          0
        ],
        "seriesMeta": [
          {
            "segmentIndex": 0,
            "eventIndex": 0
          },
          {
            "segmentIndex": 0,
            "eventIndex": 1
          },
          {
            "segmentIndex": 0,
            "eventIndex": 2
          },
          {
            "segmentIndex": 0,
            "eventIndex": 3
          }
        ],
        "xValues": [
          "2025-12-29",
          "2026-01-05",
          "2026-01-12",
          "2026-01-19",
          "2026-01-26",
          "2026-02-02",
          "2026-02-09",
          "2026-02-16",
          "2026-02-23",
          "2026-03-02",
          "2026-03-09",
          "2026-03-16",
          "2026-03-23"
        ]
      }
    },
    "engagement": {
      "chart": "1v3107dq",
      "data": {
        "series": [
          [
            {
              "setId": "",
              "value": 0
            },
            {
              "setId": "",
              "value": 0
            },
            {
              "setId": "",
              "value": 0
            },
            {
              "setId": "",
              "value": 0
            },
            {
              "setId": "",
              "value": 0
            },
            {
              "setId": "",
              "value": 0
            },
            {
              "setId": "",
              "value": 0
            },
            {
              "setId": "",
              "value": 0
            },
            {
              "setId": "",
              "value": 0
            },
            {
              "setId": "",
              "value": 0
            },
            {
              "setId": "",
              "value": 0
            },
            {
              "setId": "",
              "value": 0
            },
            {
              "setId": "",
              "value": 0
            }
          ],
          [
            {
              "setId": "",
              "value": 0
            },
            {
              "setId": "",
              "value": 0
            },
            {
              "setId": "",
              "value": 0
            },
            {
              "setId": "",
              "value": 0
            },
            {
              "setId": "",
              "value": 0
            },
            {
              "setId": "",
              "value": 0
            },
            {
              "setId": "",
              "value": 0
            },
            {
              "setId": "",
              "value": 0
            },
            {
              "setId": "",
              "value": 0
            },
            {
              "setId": "",
              "value": 0
            },
            {
              "setId": "",
              "value": 0
            },
            {
              "setId": "",
              "value": 0
            },
            {
              "setId": "",
              "value": 0
            }
          ],
          [
            {
              "setId": "",
              "value": 0
            },
            {
              "setId": "",
              "value": 0
            },
            {
              "setId": "",
              "value": 0
            },
            {
              "setId": "",
              "value": 0
            },
            {
              "setId": "",
              "value": 0
            },
            {
              "setId": "",
              "value": 0
            },
            {
              "setId": "",
              "value": 0
            },
            {
              "setId": "",
              "value": 0
            },
            {
              "setId": "",
              "value": 0
            },
            {
              "setId": "",
              "value": 0
            },
            {
              "setId": "",
              "value": 0
            },
            {
              "setId": "",
              "value": 0
            },
            {
              "setId": "",
              "value": 0
            }
          ]
        ],
        "seriesCollapsed": [
          [
            {
              "setId": "",
              "value": 0
            }
          ],
          [
            {
              "setId": "",
              "value": 0
            }
          ],
          [
            {
              "setId": "",
              "value": 0
            }
          ]
        ],
        "seriesLabels": [
          0,
          0,
          0
        ],
        "seriesMeta": [
          {
            "segmentIndex": 0,
            "eventIndex": 0
          },
          {
            "segmentIndex": 0,
            "eventIndex": 1
          },
          {
            "segmentIndex": 0,
            "eventIndex": 2
          }
        ],
        "xValues": [
          "2025-12-29",
          "2026-01-05",
          "2026-01-12",
          "2026-01-19",
          "2026-01-26",
          "2026-02-02",
          "2026-02-09",
          "2026-02-16",
          "2026-02-23",
          "2026-03-02",
          "2026-03-09",
          "2026-03-16",
          "2026-03-23"
        ]
      }
    },
    "sessionDuration": {
      "chart": "pepuaofo",
      "data": {
        "series": [
          [
            {
              "setId": "",
              "value": 38
            },
            {
              "setId": "",
              "value": 99
            },
            {
              "setId": "",
              "value": 123
            },
            {
              "setId": "",
              "value": 102
            },
            {
              "setId": "",
              "value": 105
            },
            {
              "setId": "",
              "value": 109
            },
            {
              "setId": "",
              "value": 107
            },
            {
              "setId": "",
              "value": 100
            },
            {
              "setId": "",
              "value": 119
            },
            {
              "setId": "",
              "value": 118
            },
            {
              "setId": "",
              "value": 121
            },
            {
              "setId": "",
              "value": 117
            },
            {
              "setId": "",
              "value": 50
            }
          ],
          [
            {
              "setId": "",
              "value": 5
            },
            {
              "setId": "",
              "value": 10
            },
            {
              "setId": "",
              "value": 17
            },
            {
              "setId": "",
              "value": 5
            },
            {
              "setId": "",
              "value": 11
            },
            {
              "setId": "",
              "value": 15
            },
            {
              "setId": "",
              "value": 18
            },
            {
              "setId": "",
              "value": 18
            },
            {
              "setId": "",
              "value": 13
            },
            {
              "setId": "",
              "value": 8
            },
            {
              "setId": "",
              "value": 8
            },
            {
              "setId": "",
              "value": 8
            },
            {
              "setId": "",
              "value": 6
            }
          ],
          [
            {
              "setId": "",
              "value": 3
            },
            {
              "setId": "",
              "value": 3
            },
            {
              "setId": "",
              "value": 3
            },
            {
              "setId": "",
              "value": 3
            },
            {
              "setId": "",
              "value": 1
            },
            {
              "setId": "",
              "value": 3
            },
            {
              "setId": "",
              "value": 4
            },
            {
              "setId": "",
              "value": 6
            },
            {
              "setId": "",
              "value": 4
            },
            {
              "setId": "",
              "value": 2
            },
            {
              "setId": "",
              "value": 3
            },
            {
              "setId": "",
              "value": 5
            },
            {
              "setId": "",
              "value": 1
            }
          ],
          [
            {
              "setId": "",
              "value": 71
            },
            {
              "setId": "",
              "value": 192
            },
            {
              "setId": "",
              "value": 237
            },
            {
              "setId": "",
              "value": 193
            },
            {
              "setId": "",
              "value": 194
            },
            {
              "setId": "",
              "value": 197
            },
            {
              "setId": "",
              "value": 229
            },
            {
              "setId": "",
              "value": 194
            },
            {
              "setId": "",
              "value": 244
            },
            {
              "setId": "",
              "value": 291
            },
            {
              "setId": "",
              "value": 260
            },
            {
              "setId": "",
              "value": 279
            },
            {
              "setId": "",
              "value": 142
            }
          ]
        ],
        "seriesCollapsed": [
          [
            {
              "setId": "",
              "value": 374
            }
          ],
          [
            {
              "setId": "",
              "value": 82
            }
          ],
          [
            {
              "setId": "",
              "value": 25
            }
          ],
          [
            {
              "setId": "",
              "value": 728
            }
          ]
        ],
        "seriesLabels": [
          0,
          0,
          0,
          0
        ],
        "seriesMeta": [
          {
            "segmentIndex": 0,
            "eventIndex": 0
          },
          {
            "segmentIndex": 0,
            "eventIndex": 1
          },
          {
            "segmentIndex": 0,
            "eventIndex": 2
          },
          {
            "segmentIndex": 0,
            "eventIndex": 3
          }
        ],
        "xValues": [
          "2025-12-29",
          "2026-01-05",
          "2026-01-12",
          "2026-01-19",
          "2026-01-26",
          "2026-02-02",
          "2026-02-09",
          "2026-02-16",
          "2026-02-23",
          "2026-03-02",
          "2026-03-09",
          "2026-03-16",
          "2026-03-23"
        ]
      }
    },
    "keyActions": {
      "chart": "pr53xnu5",
      "data": {
        "series": [
          [
            {
              "setId": "",
              "value": 27
            },
            {
              "setId": "",
              "value": 72
            },
            {
              "setId": "",
              "value": 215
            },
            {
              "setId": "",
              "value": 26
            },
            {
              "setId": "",
              "value": 109
            },
            {
              "setId": "",
              "value": 81
            },
            {
              "setId": "",
              "value": 125
            },
            {
              "setId": "",
              "value": 155
            },
            {
              "setId": "",
              "value": 111
            },
            {
              "setId": "",
              "value": 145
            },
            {
              "setId": "",
              "value": 48
            },
            {
              "setId": "",
              "value": 87
            },
            {
              "setId": "",
              "value": 16
            }
          ],
          [
            {
              "setId": "",
              "value": 49
            },
            {
              "setId": "",
              "value": 92
            },
            {
              "setId": "",
              "value": 320
            },
            {
              "setId": "",
              "value": 80
            },
            {
              "setId": "",
              "value": 147
            },
            {
              "setId": "",
              "value": 212
            },
            {
              "setId": "",
              "value": 178
            },
            {
              "setId": "",
              "value": 270
            },
            {
              "setId": "",
              "value": 226
            },
            {
              "setId": "",
              "value": 189
            },
            {
              "setId": "",
              "value": 264
            },
            {
              "setId": "",
              "value": 186
            },
            {
              "setId": "",
              "value": 38
            }
          ],
          [
            {
              "setId": "",
              "value": 0
            },
            {
              "setId": "",
              "value": 0
            },
            {
              "setId": "",
              "value": 0
            },
            {
              "setId": "",
              "value": 0
            },
            {
              "setId": "",
              "value": 0
            },
            {
              "setId": "",
              "value": 0
            },
            {
              "setId": "",
              "value": 0
            },
            {
              "setId": "",
              "value": 0
            },
            {
              "setId": "",
              "value": 0
            },
            {
              "setId": "",
              "value": 0
            },
            {
              "setId": "",
              "value": 0
            },
            {
              "setId": "",
              "value": 0
            },
            {
              "setId": "",
              "value": 0
            }
          ],
          [
            {
              "setId": "",
              "value": 286
            },
            {
              "setId": "",
              "value": 530
            },
            {
              "setId": "",
              "value": 719
            },
            {
              "setId": "",
              "value": 617
            },
            {
              "setId": "",
              "value": 737
            },
            {
              "setId": "",
              "value": 708
            },
            {
              "setId": "",
              "value": 817
            },
            {
              "setId": "",
              "value": 1130
            },
            {
              "setId": "",
              "value": 667
            },
            {
              "setId": "",
              "value": 630
            },
            {
              "setId": "",
              "value": 1107
            },
            {
              "setId": "",
              "value": 633
            },
            {
              "setId": "",
              "value": 140
            }
          ],
          [
            {
              "setId": "",
              "value": 0
            },
            {
              "setId": "",
              "value": 0
            },
            {
              "setId": "",
              "value": 0
            },
            {
              "setId": "",
              "value": 0
            },
            {
              "setId": "",
              "value": 0
            },
            {
              "setId": "",
              "value": 0
            },
            {
              "setId": "",
              "value": 0
            },
            {
              "setId": "",
              "value": 0
            },
            {
              "setId": "",
              "value": 0
            },
            {
              "setId": "",
              "value": 0
            },
            {
              "setId": "",
              "value": 0
            },
            {
              "setId": "",
              "value": 0
            },
            {
              "setId": "",
              "value": 0
            }
          ]
        ],
        "seriesCollapsed": [
          [
            {
              "setId": "",
              "value": 1217
            }
          ],
          [
            {
              "setId": "",
              "value": 2251
            }
          ],
          [
            {
              "setId": "",
              "value": 0
            }
          ],
          [
            {
              "setId": "",
              "value": 8721
            }
          ],
          [
            {
              "setId": "",
              "value": 0
            }
          ]
        ],
        "seriesLabels": [
          0,
          0,
          0,
          0,
          0
        ],
        "seriesMeta": [
          {
            "segmentIndex": 0,
            "eventIndex": 0
          },
          {
            "segmentIndex": 0,
            "eventIndex": 1
          },
          {
            "segmentIndex": 0,
            "eventIndex": 2
          },
          {
            "segmentIndex": 0,
            "eventIndex": 3
          },
          {
            "segmentIndex": 0,
            "eventIndex": 4
          }
        ],
        "xValues": [
          "2025-12-29",
          "2026-01-05",
          "2026-01-12",
          "2026-01-19",
          "2026-01-26",
          "2026-02-02",
          "2026-02-09",
          "2026-02-16",
          "2026-02-23",
          "2026-03-02",
          "2026-03-09",
          "2026-03-16",
          "2026-03-23"
        ]
      }
    }
  },
  "team": [
    {
      "name": "Sanghee",
      "role": "PM",
      "squad": "Core Platform",
      "status": "shipping",
      "topConcern": "Families feature moving to beta with docs and feedback integration complete",
      "linearActive": 6,
      "linearBlocked": 0,
      "slackLastSeen": "2026-03-24T09:15:00Z",
      "fourPAge": "2d",
      "meetingsToday": 3
    },
    {
      "name": "Kenn",
      "role": "PM",
      "squad": "Data Access & Governance",
      "status": "shipping",
      "topConcern": "Multiple IdP integrations shipping with internal tooling for customer onboarding",
      "linearActive": 5,
      "linearBlocked": 0,
      "slackLastSeen": "2026-03-24T10:42:00Z",
      "fourPAge": "1d",
      "meetingsToday": 2
    },
    {
      "name": "Jess",
      "role": "PM",
      "squad": "Canvas & Workflows",
      "status": "shipping",
      "topConcern": "Multi-run features and calculated channels UX improvements shipping smoothly",
      "linearActive": 4,
      "linearBlocked": 0,
      "slackLastSeen": "2026-03-24T08:30:00Z",
      "fourPAge": "3d",
      "meetingsToday": 4
    },
    {
      "name": "Rowen",
      "role": "PM",
      "squad": "Infrastructure & Security",
      "status": "shipping",
      "topConcern": "Sift Edge workflows and CLI v0.1.0 release with deployment automation complete",
      "linearActive": 8,
      "linearBlocked": 0,
      "slackLastSeen": "2026-03-24T11:20:00Z",
      "fourPAge": "1d",
      "meetingsToday": 2
    },
    {
      "name": "Kevin",
      "role": "Software Engineering Manager",
      "squad": "Engineering",
      "status": "shipping",
      "topConcern": "Team velocity strong across platform improvements and feature flag infrastructure",
      "linearActive": 12,
      "linearBlocked": 0,
      "slackLastSeen": "2026-03-24T10:05:00Z",
      "fourPAge": "1d",
      "meetingsToday": 5
    },
    {
      "name": "Gui",
      "role": "FDE Lead",
      "squad": "Field Engineering",
      "status": "shipping",
      "topConcern": "Customer feedback on Families visualization being incorporated into roadmap",
      "linearActive": 2,
      "linearBlocked": 0,
      "slackLastSeen": "2026-03-24T09:45:00Z",
      "fourPAge": "2d",
      "meetingsToday": 3
    }
  ],
  "cofounders": [
    {
      "name": "Austin",
      "role": "CEO",
      "attention": "Strong execution across product areas with families beta launch and IdP expansion",
      "recentTopics": [
        "Families feature customer adoption",
        "IdP integration strategy for enterprise customers",
        "Sift CLI release timeline"
      ],
      "lastSlackToNoah": "2026-03-23T16:30:00Z",
      "pendingDecisions": [
        "Prioritization of additional IdP integrations beyond TEC and Astrolab",
        "Resource allocation for feature flag infrastructure expansion"
      ]
    },
    {
      "name": "Karthik",
      "role": "CTO",
      "attention": "Infrastructure modernization progressing with agent-assisted incident response POC showing promise",
      "recentTopics": [
        "MCP server MVP for AI tooling",
        "Annotations caching optimization",
        "External integration testing with Checkly",
        "Feature flag infrastructure for experimentation"
      ],
      "lastSlackToNoah": "2026-03-24T07:15:00Z",
      "pendingDecisions": [
        "Adoption strategy for agent-assisted incident response beyond POC",
        "Timeline for deprecating legacy ingest_config_flows table"
      ]
    }
  ],
  "customers": [
    {
      "name": "K2 Space",
      "tier": "growth",
      "trajectory": "stable",
      "wau": 12,
      "topSignal": "Utilizing core platform features with steady engagement patterns",
      "features": [
        "data_ingestion",
        "visualization",
        "calculated_channels"
      ],
      "lastActivity": "2026-03-23T18:30:00Z",
      "openIssues": 0
    },
    {
      "name": "Astranis",
      "tier": "enterprise",
      "trajectory": "expanding",
      "wau": 28,
      "topSignal": "Heavy adoption of families feature and calculated channels in beta",
      "features": [
        "families",
        "calculated_channels",
        "multi_run_analysis",
        "annotations"
      ],
      "lastActivity": "2026-03-24T14:20:00Z",
      "openIssues": 1
    },
    {
      "name": "Reliable Robotics",
      "tier": "growth",
      "trajectory": "stable",
      "wau": 15,
      "topSignal": "Consistent usage of run analysis and visualization tools",
      "features": [
        "run_analysis",
        "visualization",
        "data_ingestion"
      ],
      "lastActivity": "2026-03-24T11:45:00Z",
      "openIssues": 0
    },
    {
      "name": "Varda",
      "tier": "enterprise",
      "trajectory": "expanding",
      "wau": 22,
      "topSignal": "Active adoption of file attachment features and custom workflows",
      "features": [
        "file_attachments",
        "data_ingestion",
        "visualization",
        "annotations"
      ],
      "lastActivity": "2026-03-24T16:10:00Z",
      "openIssues": 0
    },
    {
      "name": "Heart Aerospace",
      "tier": "growth",
      "trajectory": "stable",
      "wau": 18,
      "topSignal": "Regular platform usage with focus on telemetry analysis",
      "features": [
        "data_ingestion",
        "visualization",
        "calculated_channels"
      ],
      "lastActivity": "2026-03-23T22:15:00Z",
      "openIssues": 1
    },
    {
      "name": "Lockheed Martin",
      "tier": "enterprise",
      "trajectory": "stable",
      "wau": 45,
      "topSignal": "Large team utilization with emphasis on security and compliance features",
      "features": [
        "sso",
        "data_ingestion",
        "visualization",
        "annotations",
        "families"
      ],
      "lastActivity": "2026-03-24T15:30:00Z",
      "openIssues": 2
    },
    {
      "name": "ULA",
      "tier": "enterprise",
      "trajectory": "expanding",
      "wau": 52,
      "topSignal": "Provided feedback on Family Visualization feature, actively engaged in product development",
      "features": [
        "families",
        "visualization",
        "calculated_channels",
        "run_analysis",
        "sso"
      ],
      "lastActivity": "2026-03-24T13:50:00Z",
      "openIssues": 1
    },
    {
      "name": "Parallel Systems",
      "tier": "growth",
      "trajectory": "stable",
      "wau": 14,
      "topSignal": "Steady engagement with core telemetry features",
      "features": [
        "data_ingestion",
        "visualization",
        "run_analysis"
      ],
      "lastActivity": "2026-03-24T09:20:00Z",
      "openIssues": 0
    },
    {
      "name": "The Exploration Company",
      "tier": "enterprise",
      "trajectory": "expanding",
      "wau": 31,
      "topSignal": "IdP integration in progress, preparing for expanded team deployment",
      "features": [
        "sso",
        "data_ingestion",
        "visualization",
        "families",
        "calculated_channels"
      ],
      "lastActivity": "2026-03-24T17:05:00Z",
      "openIssues": 1
    },
    {
      "name": "OHB",
      "tier": "enterprise",
      "trajectory": "stable",
      "wau": 38,
      "topSignal": "Established customer with consistent high-volume usage",
      "features": [
        "data_ingestion",
        "visualization",
        "annotations",
        "families"
      ],
      "lastActivity": "2026-03-24T12:40:00Z",
      "openIssues": 0
    },
    {
      "name": "Dust Moto",
      "tier": "pilot",
      "trajectory": "expanding",
      "wau": 6,
      "topSignal": "Early-stage adoption showing positive engagement growth",
      "features": [
        "data_ingestion",
        "visualization"
      ],
      "lastActivity": "2026-03-24T10:15:00Z",
      "openIssues": 0
    },
    {
      "name": "Orbital Operations",
      "tier": "growth",
      "trajectory": "stable",
      "wau": 11,
      "topSignal": "Regular usage of core analysis features",
      "features": [
        "data_ingestion",
        "run_analysis",
        "visualization"
      ],
      "lastActivity": "2026-03-23T20:30:00Z",
      "openIssues": 0
    },
    {
      "name": "Inversion Space",
      "tier": "growth",
      "trajectory": "expanding",
      "wau": 16,
      "topSignal": "Increasing engagement with advanced features like calculated channels",
      "features": [
        "data_ingestion",
        "calculated_channels",
        "visualization",
        "run_analysis"
      ],
      "lastActivity": "2026-03-24T14:55:00Z",
      "openIssues": 1
    },
    {
      "name": "Revel",
      "tier": "pilot",
      "trajectory": "stable",
      "wau": 5,
      "topSignal": "Early pilot phase with consistent but limited usage",
      "features": [
        "data_ingestion",
        "visualization"
      ],
      "lastActivity": "2026-03-23T16:45:00Z",
      "openIssues": 0
    },
    {
      "name": "CX2",
      "tier": "pilot",
      "trajectory": "at-risk",
      "wau": 2,
      "topSignal": "Low engagement, potential churn risk without intervention",
      "features": [
        "data_ingestion"
      ],
      "lastActivity": "2026-03-19T11:20:00Z",
      "openIssues": 1
    },
    {
      "name": "Also",
      "tier": "pilot",
      "trajectory": "stable",
      "wau": 4,
      "topSignal": "Small team evaluation with steady usage patterns",
      "features": [
        "data_ingestion",
        "visualization"
      ],
      "lastActivity": "2026-03-24T08:30:00Z",
      "openIssues": 0
    },
    {
      "name": "Arbor Energy",
      "tier": "growth",
      "trajectory": "stable",
      "wau": 13,
      "topSignal": "Consistent usage focused on data pipeline optimization",
      "features": [
        "data_ingestion",
        "visualization",
        "calculated_channels"
      ],
      "lastActivity": "2026-03-24T13:15:00Z",
      "openIssues": 0
    },
    {
      "name": "Synnax",
      "tier": "pilot",
      "trajectory": "expanding",
      "wau": 7,
      "topSignal": "Positive pilot trajectory with growing feature adoption",
      "features": [
        "data_ingestion",
        "visualization",
        "run_analysis"
      ],
      "lastActivity": "2026-03-24T15:50:00Z",
      "openIssues": 0
    },
    {
      "name": "OdysAviation",
      "tier": "growth",
      "trajectory": "stable",
      "wau": 10,
      "topSignal": "Regular platform usage for flight test analysis",
      "features": [
        "data_ingestion",
        "visualization",
        "annotations"
      ],
      "lastActivity": "2026-03-24T11:00:00Z",
      "openIssues": 0
    },
    {
      "name": "CriticalLoop",
      "tier": "pilot",
      "trajectory": "stable",
      "wau": 5,
      "topSignal": "Pilot phase with baseline engagement",
      "features": [
        "data_ingestion",
        "visualization"
      ],
      "lastActivity": "2026-03-23T19:25:00Z",
      "openIssues": 0
    },
    {
      "name": "RadTeam",
      "tier": "pilot",
      "trajectory": "expanding",
      "wau": 6,
      "topSignal": "Growing interest in advanced telemetry capabilities",
      "features": [
        "data_ingestion",
        "visualization",
        "calculated_channels"
      ],
      "lastActivity": "2026-03-24T16:40:00Z",
      "openIssues": 0
    },
    {
      "name": "Starpath",
      "tier": "growth",
      "trajectory": "stable",
      "wau": 9,
      "topSignal": "Steady adoption with focus on core observability features",
      "features": [
        "data_ingestion",
        "visualization",
        "run_analysis"
      ],
      "lastActivity": "2026-03-24T10:45:00Z",
      "openIssues": 0
    },
    {
      "name": "Astrolab",
      "tier": "enterprise",
      "trajectory": "expanding",
      "wau": 27,
      "topSignal": "SSO integration in progress, preparing for team-wide rollout",
      "features": [
        "sso",
        "data_ingestion",
        "visualization",
        "families",
        "annotations"
      ],
      "lastActivity": "2026-03-24T14:30:00Z",
      "openIssues": 1
    },
    {
      "name": "AstroMecha",
      "tier": "pilot",
      "trajectory": "stable",
      "wau": 4,
      "topSignal": "Early evaluation phase with consistent usage",
      "features": [
        "data_ingestion",
        "visualization"
      ],
      "lastActivity": "2026-03-23T17:10:00Z",
      "openIssues": 0
    },
    {
      "name": "Neros",
      "tier": "pilot",
      "trajectory": "expanding",
      "wau": 8,
      "topSignal": "Strong pilot engagement with expanding feature exploration",
      "features": [
        "data_ingestion",
        "visualization",
        "run_analysis",
        "calculated_channels"
      ],
      "lastActivity": "2026-03-24T12:20:00Z",
      "openIssues": 0
    },
    {
      "name": "Zipline",
      "tier": "enterprise",
      "trajectory": "stable",
      "wau": 42,
      "topSignal": "Large-scale deployment with mature usage patterns",
      "features": [
        "data_ingestion",
        "visualization",
        "annotations",
        "families",
        "run_analysis"
      ],
      "lastActivity": "2026-03-24T16:25:00Z",
      "openIssues": 1
    },
    {
      "name": "PlantD",
      "tier": "pilot",
      "trajectory": "at-risk",
      "wau": 3,
      "topSignal": "Limited engagement, needs outreach to maintain momentum",
      "features": [
        "data_ingestion",
        "visualization"
      ],
      "lastActivity": "2026-03-20T14:50:00Z",
      "openIssues": 0
    },
    {
      "name": "Halo One",
      "tier": "growth",
      "trajectory": "stable",
      "wau": 12,
      "topSignal": "Consistent usage with solid engagement metrics",
      "features": [
        "data_ingestion",
        "visualization",
        "run_analysis"
      ],
      "lastActivity": "2026-03-24T09:55:00Z",
      "openIssues": 0
    },
    {
      "name": "First Resonance",
      "tier": "growth",
      "trajectory": "stable",
      "wau": 14,
      "topSignal": "Regular platform usage for manufacturing telemetry",
      "features": [
        "data_ingestion",
        "visualization",
        "calculated_channels"
      ],
      "lastActivity": "2026-03-24T13:40:00Z",
      "openIssues": 0
    },
    {
      "name": "Manufacturo",
      "tier": "pilot",
      "trajectory": "stable",
      "wau": 5,
      "topSignal": "Pilot evaluation with baseline engagement",
      "features": [
        "data_ingestion",
        "visualization"
      ],
      "lastActivity": "2026-03-23T21:15:00Z",
      "openIssues": 0
    },
    {
      "name": "AstroForge",
      "tier": "growth",
      "trajectory": "expanding",
      "wau": 17,
      "topSignal": "Growing adoption with increased team usage and feature exploration",
      "features": [
        "data_ingestion",
        "visualization",
        "calculated_channels",
        "families"
      ],
      "lastActivity": "2026-03-24T15:10:00Z",
      "openIssues": 0
    },
    {
      "name": "Exdanris",
      "tier": "pilot",
      "trajectory": "stable",
      "wau": 4,
      "topSignal": "Early-stage pilot with consistent baseline usage",
      "features": [
        "data_ingestion",
        "visualization"
      ],
      "lastActivity": "2026-03-24T11:30:00Z",
      "openIssues": 0
    }
  ],
  "decisions": [
    {
      "title": "Prioritize Families feature GA vs Beta extension",
      "context": "DES-113 surfaced ULA customer feedback on Family Visualization, DOC-16 and ENG-9499 are building docs, ENG-9556 labels it Beta. Need to decide: commit to GA timeline or extend Beta for more feedback cycles.",
      "owner": "Product & Eng Leadership",
      "deadline": "2026-04-07",
      "status": "open",
      "blockedBy": "",
      "arguments": {
        "for": "Customer feedback is actionable, docs in progress, signals show momentum toward stabilization",
        "against": "Beta label suggests feature incomplete; rushing GA risks quality issues that damage trust"
      }
    },
    {
      "title": "Commit resources to MCP/Agent incident response vs core product velocity",
      "context": "ENG-9296 (Internal MCP server MVP) and ENG-9292 (Agent-assisted incident response POC) represent new AI/automation direction. Competes with core Canvas, Python Rules, Explore V2 roadmap bandwidth.",
      "owner": "CTO & VP Product",
      "deadline": "2026-04-14",
      "status": "open",
      "blockedBy": "",
      "arguments": {
        "for": "MCP/Agent aligns with 'Build the Moat'—differentiated AI-driven workflows. Early POCs can unlock Ask SIFT v2 capabilities.",
        "against": "Team capacity finite; diverting from Nail the Core risks slowing Decisions Captured Per Customer growth"
      }
    },
    {
      "title": "Standardize IdP integration approach for all enterprise customers",
      "context": "ENG-8081 (TEC), ENG-8157 (Astrolab), ENG-9613 (onboarding tool), ENG-9614 (metrics/alerts) show ad-hoc IdP work. Need architectural decision: per-customer custom vs standardized SSO framework.",
      "owner": "Engineering Leadership",
      "deadline": "2026-03-31",
      "status": "blocked",
      "blockedBy": "Lack of clarity on enterprise customer SSO requirements matrix; security team audit pending",
      "arguments": {
        "for": "Standardization scales Embed Deeper pillar; reduces maintenance burden, accelerates onboarding",
        "against": "Custom integrations may be necessary for high-value customers with unique identity stacks"
      }
    },
    {
      "title": "Feature flag rollout strategy: event tracking vs session replay priority",
      "context": "ENG-9125 (Event Feature Flagged Experiences), ENG-9124 (Session Replay), ENG-9122 (Discovery prototypes) in flight. Must decide: ship event tracking first for faster iteration or wait for session replay for richer debugging.",
      "owner": "Product Manager - Core Platform",
      "deadline": "2026-04-01",
      "status": "open",
      "blockedBy": "",
      "arguments": {
        "for": "Event tracking ships faster, unblocks A/B testing for Canvas/Explore V2 features sooner",
        "against": "Session replay provides deeper signal for complex UX decisions; waiting delivers better long-term insights"
      }
    },
    {
      "title": "Sift CLI v0.1.0 release scope: MVP now vs expanded features",
      "context": "ENG-9569 signals CLI v0.1.0 imminent. Decision: ship minimal viable CLI for early adopters or expand scope to include Python Rules authoring, bulk operations.",
      "owner": "Eng Lead - Developer Experience",
      "deadline": "2026-03-28",
      "status": "open",
      "blockedBy": "",
      "arguments": {
        "for": "MVP unblocks power users immediately; establishes feedback loop for v0.2 prioritization",
        "against": "Narrow feature set may disappoint expectations; risks low adoption if missing key workflows"
      }
    }
  ],
  "strategyMetrics": {
    "northStar": {
      "name": "Decisions Captured Per Customer",
      "value": "127",
      "delta": "+8%"
    },
    "pillars": [
      {
        "name": "Nail the Core",
        "status": "on_track",
        "keyResults": [
          {
            "name": "Explore V2 DAU/MAU ratio",
            "current": "0.41",
            "target": "0.50",
            "status": "at_risk"
          },
          {
            "name": "Canvas collaboration sessions per week",
            "current": "342",
            "target": "500",
            "status": "on_track"
          },
          {
            "name": "Python Rules deployed per customer",
            "current": "3.2",
            "target": "5.0",
            "status": "at_risk"
          }
        ]
      },
      {
        "name": "Embed Deeper",
        "status": "at_risk",
        "keyResults": [
          {
            "name": "IdP-integrated customers",
            "current": "12",
            "target": "25",
            "status": "at_risk"
          },
          {
            "name": "API calls per active customer",
            "current": "1847",
            "target": "3000",
            "status": "on_track"
          },
          {
            "name": "Sift CLI active users (beta)",
            "current": "0",
            "target": "15",
            "status": "at_risk"
          }
        ]
      },
      {
        "name": "Build the Moat",
        "status": "on_track",
        "keyResults": [
          {
            "name": "Ask SIFT query accuracy",
            "current": "78%",
            "target": "85%",
            "status": "on_track"
          },
          {
            "name": "Sift Edge deployments",
            "current": "8",
            "target": "20",
            "status": "on_track"
          },
          {
            "name": "MCP/Agent POC customer pilots",
            "current": "0",
            "target": "3",
            "status": "on_track"
          }
        ]
      }
    ]
  },
  "timeAudit": {
    "today": {
      "date": "2026-03-24",
      "meetings": 5,
      "focusBlocks": 2,
      "oneOnOnes": 3,
      "freeHours": 2,
      "meetingHours": 6
    },
    "thisWeek": {
      "meetings": 22,
      "freeHours": 8,
      "meetingHours": 32
    },
    "weekSummary": "Heavy coordination week: IdP integrations, Families feedback synthesis, CLI release planning consuming most meeting time. Focus blocks insufficient for deep product strategy work.",
    "alerts": [
      "3 decisions pending past original target dates (IdP standardization blocking customer onboarding)",
      "Eng team context-switching between 9 active Linear projects; fragmentation risk to velocity",
      "No dedicated time blocked for 2026 H2 strategy planning (due April 15); calendar fully booked"
    ]
  },
  "timeline": {
    "sections": [
      {
        "label": "This Week (Mar 24-30)",
        "events": [
          {
            "title": "Sift CLI v0.1.0 Release Decision",
            "date": "2026-03-28",
            "time": "14:00",
            "type": "gate",
            "description": "Ship/hold decision for CLI MVP; ENG-9569 completion pending",
            "owner": "Eng Lead - DevEx"
          },
          {
            "title": "Families Beta Documentation Published",
            "date": "2026-03-27",
            "time": "17:00",
            "type": "milestone",
            "description": "DOC-16 and ENG-9499 complete; unblocks customer self-service",
            "owner": "Tech Writer & Eng"
          },
          {
            "title": "Feature Flag Architecture Review",
            "date": "2026-03-26",
            "time": "10:00",
            "type": "meeting",
            "description": "ENG-9125/9124/9122 alignment session; decide event vs replay priority",
            "owner": "PM - Core Platform"
          }
        ]
      },
      {
        "label": "Next 2 Weeks (Mar 31-Apr 13)",
        "events": [
          {
            "title": "IdP Integration Standardization Decision",
            "date": "2026-03-31",
            "time": "15:00",
            "type": "deadline",
            "description": "Resolve ENG-8081/8157/9613/9614 into unified SSO strategy",
            "owner": "Engineering Leadership"
          },
          {
            "title": "Feature Flag Event Tracking Shipped",
            "date": "2026-04-01",
            "time": "18:00",
            "type": "milestone",
            "description": "ENG-9125 deployed; enables A/B testing for Canvas features",
            "owner": "PM - Core Platform"
          },
          {
            "title": "Families GA/Extended Beta Decision",
            "date": "2026-04-07",
            "time": "13:00",
            "type": "gate",
            "description": "Based on DES-113 ULA feedback; commit to GA timeline or extend Beta",
            "owner": "Product & Eng Leadership"
          },
          {
            "title": "Q2 Product Strategy Offsite",
            "date": "2026-04-10",
            "time": "09:00",
            "type": "meeting",
            "description": "Review Nail/Embed/Build pillar progress; finalize H2 roadmap priorities",
            "owner": "CPO"
          },
          {
            "title": "MCP/Agent POC Resource Allocation Decision",
            "date": "2026-04-14",
            "time": "14:00",
            "type": "deadline",
            "description": "Commit engineering bandwidth to ENG-9296/9292 or defer for core work",
            "owner": "CTO & VP Product"
          }
        ]
      },
      {
        "label": "This Month (Apr 15-30)",
        "events": [
          {
            "title": "Sift Edge GHA Workflow Production Ready",
            "date": "2026-04-18",
            "time": "17:00",
            "type": "milestone",
            "description": "ENG-9603 complete; enables automated Sift Edge deployments",
            "owner": "Eng - Edge Team"
          },
          {
            "title": "Calculated Channels Multi-Run UX Shipped",
            "date": "2026-04-22",
            "time": "18:00",
            "type": "milestone",
            "description": "DES-152 deployed; unblocks comparative analysis workflows",
            "owner": "Design & Eng"
          },
          {
            "title": "IdP Onboarding Tool Beta Launch",
            "date": "2026-04-25",
            "time": "10:00",
            "type": "milestone",
            "description": "ENG-9613 live; reduces enterprise customer time-to-value",
            "owner": "Eng - Platform"
          },
          {
            "title": "H2 2026 Strategy Presentation",
            "date": "2026-04-30",
            "time": "15:00",
            "type": "meeting",
            "description": "All-hands rollout of updated roadmap; align org on priorities",
            "owner": "Executive Team"
          }
        ]
      },
      {
        "label": "Q2 Horizon (May-Jun)",
        "events": [
          {
            "title": "Explore V2 Pathname Migration Complete",
            "date": "2026-05-15",
            "time": "17:00",
            "type": "milestone",
            "description": "ENG-9550 deployed; eliminates legacy routing tech debt",
            "owner": "Eng - Core Product"
          },
          {
            "title": "Python Rules V2 Beta Launch",
            "date": "2026-05-30",
            "time": "10:00",
            "type": "milestone",
            "description": "Major version with improved authoring UX; targets 5 rules/customer",
            "owner": "PM - Rules & Eng"
          },
          {
            "title": "Ask SIFT Accuracy Milestone (85%)",
            "date": "2026-06-15",
            "time": "18:00",
            "type": "milestone",
            "description": "Moat KR achieved; demonstrates AI-driven insight differentiation",
            "owner": "ML Team Lead"
          },
          {
            "title": "Canvas Collaboration 500 Sessions/Week",
            "date": "2026-06-30",
            "time": "17:00",
            "type": "milestone",
            "description": "Nail the Core KR hit; validates collaborative decision workflows",
            "owner": "PM - Canvas"
          }
        ]
      }
    ]
  },
  "voc": {
    "customers": []
  }
}